pytest_ampel/__init__.py
pytest_ampel/plugin.py
pytest_ampel_core-0.10.0a5.dist-info/METADATA
pytest_ampel_core-0.10.0a5.dist-info/WHEEL
pytest_ampel_core-0.10.0a5.dist-info/entry_points.txt
pytest_ampel_core-0.10.0a5.dist-info/licenses/LICENSE
pytest_ampel_core-0.10.0a5.dist-info/RECORD
