Metadata-Version: 2.4
Name: pytest-ampel-core
Version: 0.10.0a5
Summary: A plugin to provide AmpelContext fixtures in pytest
License-Expression: BSD-3-Clause
License-File: LICENSE
Author: Jakob van Santen
Author-email: jakob.van.santen@desy.de
Maintainer: Jakob van Santen
Maintainer-email: jakob.van.santen@desy.de
Requires-Python: >=3.10, <4
Classifier: Framework :: Pytest
Classifier: Development Status :: 4 - Beta
Classifier: Intended Audience :: Developers
Classifier: Topic :: Software Development :: Testing
Classifier: Operating System :: OS Independent
Classifier: Programming Language :: Python
Classifier: Programming Language :: Python :: 3.8
Classifier: Programming Language :: Python :: 3.9
Classifier: Programming Language :: Python :: 3.10
Classifier: Programming Language :: Python :: 3.11
Classifier: Programming Language :: Python :: 3.12
Classifier: Programming Language :: Python :: 3 :: Only
Classifier: Programming Language :: Python :: Implementation :: CPython
Classifier: Programming Language :: Python :: Implementation :: PyPy
Requires-Dist: ampel-core (>=0.10.6a17,<0.11)
Requires-Dist: mongomock (>=4.3.0,<5.0.0)
Requires-Dist: pytest (>=6.2.0)
Project-URL: Repository, https://github.com/AmpelProject/pytest-ampel-core
